BeatPrints/__init__.py
BeatPrints/assets/fonts/NotoSans/NotoSans-Bold.ttf
BeatPrints/assets/fonts/NotoSans/NotoSans-Light.ttf
BeatPrints/assets/fonts/NotoSans/NotoSans-Regular.ttf
BeatPrints/assets/fonts/NotoSansJP/NotoSansJP-Bold.ttf
BeatPrints/assets/fonts/NotoSansJP/NotoSansJP-Light.ttf
BeatPrints/assets/fonts/NotoSansJP/NotoSansJP-Regular.ttf
BeatPrints/assets/fonts/NotoSansKR/NotoSansKR-Bold.ttf
BeatPrints/assets/fonts/NotoSansKR/NotoSansKR-Light.ttf
BeatPrints/assets/fonts/NotoSansKR/NotoSansKR-Regular.ttf
BeatPrints/assets/fonts/NotoSansSC/NotoSansSC-Bold.ttf
BeatPrints/assets/fonts/NotoSansSC/NotoSansSC-Light.ttf
BeatPrints/assets/fonts/NotoSansSC/NotoSansSC-Regular.ttf
BeatPrints/assets/fonts/NotoSansTC/NotoSansTC-Bold.ttf
BeatPrints/assets/fonts/NotoSansTC/NotoSansTC-Light.ttf
BeatPrints/assets/fonts/NotoSansTC/NotoSansTC-Regular.ttf
BeatPrints/assets/fonts/Oswald/Oswald-Bold.ttf
BeatPrints/assets/fonts/Oswald/Oswald-Light.ttf
BeatPrints/assets/fonts/Oswald/Oswald-Regular.ttf
BeatPrints/assets/templates/catppuccin.png
BeatPrints/assets/templates/dark.png
BeatPrints/assets/templates/everforest.png
BeatPrints/assets/templates/gruvbox.png
BeatPrints/assets/templates/light.png
BeatPrints/assets/templates/nord.png
BeatPrints/assets/templates/rosepine.png
BeatPrints/consts.py
BeatPrints/errors.py
BeatPrints/image.py
BeatPrints/lyrics.py
BeatPrints/poster.py
BeatPrints/spotify.py
BeatPrints/utils.py
BeatPrints/write.py
cli/__init__.py
cli/conf.py
cli/exutils.py
cli/prompt.py
cli/validate.py
beatprints-1.1.5.dist-info/LICENSE
beatprints-1.1.5.dist-info/METADATA
beatprints-1.1.5.dist-info/WHEEL
beatprints-1.1.5.dist-info/entry_points.txt
beatprints-1.1.5.dist-info/RECORD
