Metadata-Version: 2.3
Name: BeatPrints
Version: 1.1.5
Summary: Create eye-catching, pinterest-style music posters effortlessly.
License: CC-BY-NC-4.0
Keywords: spotify,lyrics,pinterest,lrclibapi
Author: elysianmyst
Author-email: 74355265+TrueMyst@users.noreply.github.com
Requires-Python: >=3.10,<4.0
Classifier: License :: Other/Proprietary License
Classifier: Programming Language :: Python :: 3
Classifier: Programming Language :: Python :: 3.10
Classifier: Programming Language :: Python :: 3.11
Classifier: Programming Language :: Python :: 3.12
Classifier: Programming Language :: Python :: 3.13
Requires-Dist: fonttools (>=4.54.1,<5.0.0)
Requires-Dist: lrclibapi (>=0.3.1,<0.4.0)
Requires-Dist: pillow (>=9.3,<11.0)
Requires-Dist: pylette (>=4.0.0,<5.0.0)
Requires-Dist: questionary (>=2.0.1,<3.0.0)
Requires-Dist: requests (>=2.32.3,<3.0.0)
Requires-Dist: rich (>=13.9.4,<14.0.0)
Requires-Dist: spotipy (>=2.25.1,<3.0.0)
Requires-Dist: toml (>=0.10.2,<0.11.0)
Project-URL: Repository, https://github.com/TrueMyst/BeatPrints
